alchemy_provider/__init__.py
alchemy_provider/clause_binder/__init__.py
alchemy_provider/clause_binder/abstract_clause_binder.py
alchemy_provider/clause_binder/base.py
alchemy_provider/clause_binder/clause_binder.py
alchemy_provider/clause_binder/self_method_binder.py
alchemy_provider/clause_binder/string_clause_binder.py
alchemy_provider/provider/__init__.py
alchemy_provider/provider/abstract_provider.py
alchemy_provider/provider/base.py
alchemy_provider/provider/count_provider.py
alchemy_provider/provider/delete_provider.py
alchemy_provider/provider/insert_provider.py
alchemy_provider/provider/join_provider.py
alchemy_provider/provider/pagination_provider.py
alchemy_provider/provider/provider.py
alchemy_provider/provider/select_provider.py
alchemy_provider/provider/sorting_provider.py
alchemy_provider/provider/update_provider.py
alchemy_provider/provider/upsert_provider.py
alchemy_provider/query/__init__.py
alchemy_provider/query/abstract_query.py
alchemy_provider/query/base.py
alchemy_provider/query/crud_query.py
alchemy_provider/query/delete_query.py
alchemy_provider/query/field.py
alchemy_provider/query/from_query.py
alchemy_provider/query/from_row.py
alchemy_provider/query/insert_query.py
alchemy_provider/query/join_query.py
alchemy_provider/query/pagination_query.py
alchemy_provider/query/query.py
alchemy_provider/query/select_query.py
alchemy_provider/query/sorting_query.py
alchemy_provider/query/update_query.py
alchemy_provider/utils/__init__.py
alchemy_provider/utils/alchemy_orm.py
alchemy_provider/utils/aliased_manager.py
alchemy_provider/utils/cls_or_ins.py
alchemy_provider-0.0.10.dist-info/LICENSE
alchemy_provider-0.0.10.dist-info/METADATA
alchemy_provider-0.0.10.dist-info/WHEEL
alchemy_provider-0.0.10.dist-info/top_level.txt
alchemy_provider-0.0.10.dist-info/RECORD
